corider/__init__.py
corider/config.py
corider/utils.py
corider-0.1.5.dist-info/LICENSE
corider-0.1.5.dist-info/METADATA
corider-0.1.5.dist-info/WHEEL
corider-0.1.5.dist-info/top_level.txt
corider-0.1.5.dist-info/RECORD
